<annotation>
	<folder>jpeg</folder>
	<filename>lot_plan_010a62.jpg</filename>
	<path>/home/sunwu/Desktop/EC500K1/jpeg/lot_plan_010a62.jpg</path>
	<source>
		<database>Unknown</database>
	</source>
	<size>
		<width>3309</width>
		<height>2339</height>
		<depth>3</depth>
	</size>
	<segmented>0</segmented>
	<object>
		<name>WC</name>
		<pose>Unspecified</pose>
		<truncated>0</truncated>
		<difficult>0</difficult>
		<bndbox>
			<xmin>940</xmin>
			<ymin>624</ymin>
			<xmax>1176</xmax>
			<ymax>912</ymax>
		</bndbox>
	</object>
	<object>
		<name>WC</name>
		<pose>Unspecified</pose>
		<truncated>0</truncated>
		<difficult>0</difficult>
		<bndbox>
			<xmin>1110</xmin>
			<ymin>1685</ymin>
			<xmax>1262</xmax>
			<ymax>1826</ymax>
		</bndbox>
	</object>
	<object>
		<name>SDB</name>
		<pose>Unspecified</pose>
		<truncated>0</truncated>
		<difficult>0</difficult>
		<bndbox>
			<xmin>1179</xmin>
			<ymin>1826</ymin>
			<xmax>1386</xmax>
			<ymax>2007</ymax>
		</bndbox>
	</object>
</annotation>
