<annotation>
	<folder>jpeg</folder>
	<filename>lot_plan_01C401.jpg</filename>
	<path>/home/sunwu/Desktop/EC500K1/jpeg/lot_plan_01C401.jpg</path>
	<source>
		<database>Unknown</database>
	</source>
	<size>
		<width>1654</width>
		<height>2339</height>
		<depth>3</depth>
	</size>
	<segmented>0</segmented>
	<object>
		<name>WC</name>
		<pose>Unspecified</pose>
		<truncated>0</truncated>
		<difficult>0</difficult>
		<bndbox>
			<xmin>1034</xmin>
			<ymin>1058</ymin>
			<xmax>1192</xmax>
			<ymax>1221</ymax>
		</bndbox>
	</object>
	<object>
		<name>SDB</name>
		<pose>Unspecified</pose>
		<truncated>0</truncated>
		<difficult>0</difficult>
		<bndbox>
			<xmin>956</xmin>
			<ymin>1380</ymin>
			<xmax>1236</xmax>
			<ymax>1653</ymax>
		</bndbox>
	</object>
</annotation>
